japanese_needlehaystack/PaulGrahamEssays/addiction.txt
japanese_needlehaystack/PaulGrahamEssays/aord.txt
japanese_needlehaystack/PaulGrahamEssays/apple.txt
japanese_needlehaystack/PaulGrahamEssays/avg.txt
japanese_needlehaystack/PaulGrahamEssays/before.txt
japanese_needlehaystack/PaulGrahamEssays/bias.txt
japanese_needlehaystack/PaulGrahamEssays/boss.txt
japanese_needlehaystack/PaulGrahamEssays/copy.txt
japanese_needlehaystack/PaulGrahamEssays/corpdev.txt
japanese_needlehaystack/PaulGrahamEssays/desres.txt
japanese_needlehaystack/PaulGrahamEssays/diff.txt
japanese_needlehaystack/PaulGrahamEssays/ecw.txt
japanese_needlehaystack/PaulGrahamEssays/founders.txt
japanese_needlehaystack/PaulGrahamEssays/foundervisa.txt
japanese_needlehaystack/PaulGrahamEssays/gap.txt
japanese_needlehaystack/PaulGrahamEssays/gba.txt
japanese_needlehaystack/PaulGrahamEssays/gh.txt
japanese_needlehaystack/PaulGrahamEssays/goodtaste.txt
japanese_needlehaystack/PaulGrahamEssays/hubs.txt
japanese_needlehaystack/PaulGrahamEssays/iflisp.txt
japanese_needlehaystack/PaulGrahamEssays/island.txt
japanese_needlehaystack/PaulGrahamEssays/know.txt
japanese_needlehaystack/PaulGrahamEssays/langdes.txt
japanese_needlehaystack/PaulGrahamEssays/laundry.txt
japanese_needlehaystack/PaulGrahamEssays/love.txt
japanese_needlehaystack/PaulGrahamEssays/mod.txt
japanese_needlehaystack/PaulGrahamEssays/newideas.txt
japanese_needlehaystack/PaulGrahamEssays/nft.txt
japanese_needlehaystack/PaulGrahamEssays/philosophy.txt
japanese_needlehaystack/PaulGrahamEssays/popular.txt
japanese_needlehaystack/PaulGrahamEssays/pow.txt
japanese_needlehaystack/PaulGrahamEssays/rootsoflisp.txt
japanese_needlehaystack/PaulGrahamEssays/rss.txt
japanese_needlehaystack/PaulGrahamEssays/siliconvalley.txt
japanese_needlehaystack/PaulGrahamEssays/startuplessons.txt
japanese_needlehaystack/PaulGrahamEssays/submarine.txt
japanese_needlehaystack/PaulGrahamEssays/sun.txt
japanese_needlehaystack/PaulGrahamEssays/superangels.txt
japanese_needlehaystack-0.1.14.dist-info/LICENSE.txt
japanese_needlehaystack-0.1.14.dist-info/METADATA
japanese_needlehaystack-0.1.14.dist-info/WHEEL
japanese_needlehaystack-0.1.14.dist-info/entry_points.txt
japanese_needlehaystack-0.1.14.dist-info/RECORD
