Metadata-Version: 2.1
Name: japanese_needlehaystack
Version: 0.1.14
Summary: https://github.com/gkamradt/LLMTest_NeedleInAHaystack を元にいくつか修正を加えたものです。
Home-page: https://github.com/fufufukakaka/LLMTest_NeedleInAHaystack
License: MIT
Author: fufufukakaka
Author-email: demonstrundum@gmail.com
Requires-Python: >=3.9,<4.0
Classifier: License :: OSI Approved :: MIT License
Classifier: Programming Language :: Python :: 3
Classifier: Programming Language :: Python :: 3.9
Classifier: Programming Language :: Python :: 3.10
Classifier: Programming Language :: Python :: 3.11
Classifier: Programming Language :: Python :: 3.12
Requires-Dist: anthropic (>=0.31.2,<0.32.0)
Requires-Dist: google-generativeai (>=0.7.2,<0.8.0)
Requires-Dist: httpx (>=0.27.0,<0.28.0)
Requires-Dist: jsonargparse (>=4.32.0,<5.0.0)
Requires-Dist: langchain (>=0.2.10,<0.3.0)
Requires-Dist: langchain-anthropic (>=0.1.20,<0.2.0)
Requires-Dist: langchain-community (>=0.2.9,<0.3.0)
Requires-Dist: langchain-google-vertexai (>=1.0.8,<2.0.0)
Requires-Dist: langchain-openai (>=0.1.17,<0.2.0)
Requires-Dist: langsmith (>=0.1.93,<0.2.0)
Requires-Dist: openai (>=1.36.1,<2.0.0)
Requires-Dist: pydantic (>=2.8.2,<3.0.0)
Requires-Dist: pytest (>=8.3.1,<9.0.0)
Requires-Dist: python-dotenv (>=1.0.1,<2.0.0)
Requires-Dist: pyyaml (>=6.0.1,<7.0.0)
Requires-Dist: requests (>=2.32.3,<3.0.0)
Requires-Dist: sentencepiece (>=0.2.0,<0.3.0)
Requires-Dist: sqlalchemy (>=2.0.31,<3.0.0)
Requires-Dist: tenacity (>=8.5.0,<9.0.0)
Requires-Dist: tiktoken (>=0.7.0,<0.8.0)
Requires-Dist: tokenizers (>=0.19.1,<0.20.0)
Requires-Dist: tqdm (>=4.66.4,<5.0.0)
Project-URL: Repository, https://github.com/fufufukakaka/LLMTest_NeedleInAHaystack
